system_info_mcp/__init__.py
system_info_mcp/server.py
system_info_mcp_server-1.0.1.dist-info/METADATA
system_info_mcp_server-1.0.1.dist-info/WHEEL
system_info_mcp_server-1.0.1.dist-info/entry_points.txt
system_info_mcp_server-1.0.1.dist-info/RECORD
