Metadata-Version: 2.4
Name: system-info-mcp-server
Version: 1.0.1
Summary: System Information MCP Server for Claude Desktop - Get real-time system information
Project-URL: Documentation, https://github.com/username/system-info-mcp-server#readme
Project-URL: Issues, https://github.com/username/system-info-mcp-server/issues
Project-URL: Source, https://github.com/username/system-info-mcp-server
Author: Sujan Annem
License-Expression: MIT
Keywords: claude,desktop,mcp,model-context-protocol,system-info
Classifier: Development Status :: 5 - Production/Stable
Classifier: Intended Audience :: Developers
Classifier: License :: OSI Approved :: MIT License
Classifier: Operating System :: OS Independent
Classifier: Programming Language :: Python :: 3
Classifier: Programming Language :: Python :: 3.8
Classifier: Programming Language :: Python :: 3.9
Classifier: Programming Language :: Python :: 3.10
Classifier: Programming Language :: Python :: 3.11
Classifier: Programming Language :: Python :: 3.12
Classifier: Topic :: Software Development :: Libraries :: Python Modules
Classifier: Topic :: System :: Monitoring
Requires-Python: >=3.8
Requires-Dist: mcp>=1.0.0
Requires-Dist: psutil>=5.9.0
Requires-Dist: screeninfo>=0.8.1
